rpa_tracker/__init__.py
rpa_tracker/catalog/__init__.py
rpa_tracker/catalog/platform.py
rpa_tracker/catalog/registry.py
rpa_tracker/constants.py
rpa_tracker/domain/__init__.py
rpa_tracker/domain/execution_result.py
rpa_tracker/enums.py
rpa_tracker/models/__init__.py
rpa_tracker/models/tx_event.py
rpa_tracker/models/tx_process.py
rpa_tracker/models/tx_stage.py
rpa_tracker/reporting/__init__.py
rpa_tracker/reporting/transaction_report_repository.py
rpa_tracker/retry/__init__.py
rpa_tracker/retry/policy.py
rpa_tracker/retry/registry.py
rpa_tracker/tracking/__init__.py
rpa_tracker/tracking/deduplication/__init__.py
rpa_tracker/tracking/deduplication/base.py
rpa_tracker/tracking/deduplication/registry.py
rpa_tracker/tracking/sql_tracker.py
rpa_tracker/tracking/transaction_tracker.py
rpa_tracker-0.0.17.dist-info/METADATA
rpa_tracker-0.0.17.dist-info/WHEEL
rpa_tracker-0.0.17.dist-info/licenses/LICENSE
rpa_tracker-0.0.17.dist-info/RECORD
