Metadata-Version: 2.4
Name: rpa-tracker
Version: 0.0.17
Summary: Transaction tracking, deduplication, retry handling and audit trail for Python-based RPA and backend automation.
License: GPL-3.0-only
License-File: LICENSE
Author: Jonathan Bolo
Author-email: jbolo.des@gmail.com
Requires-Python: >=3.9,<3.13
Classifier: Intended Audience :: Developers
Classifier: License :: OSI Approved :: GNU General Public License v3 (GPLv3)
Classifier: Programming Language :: Python :: 3
Classifier: Programming Language :: Python :: 3.9
Classifier: Programming Language :: Python :: 3.10
Classifier: Programming Language :: Python :: 3.11
Classifier: Programming Language :: Python :: 3.12
Classifier: Topic :: Software Development :: Libraries
Classifier: Topic :: Utilities
Requires-Dist: pydantic (>=2.5,<3.0)
Requires-Dist: sqlalchemy (>=2.0.45,<3.0.0)
